{
  "About": "About",
  "Authorization form": "Authorization form",
  "Edit": "Edit",
  "Enter": "Enter",
  "Enter your firstname": "Enter your firstname",
  "Enter your lastname": "Enter your lastname",
  "Field": "Field",
  "Firstname": "Firstname",
  "Go to home page": "Go to home page",
  "Lastname": "Lastname",
  "Login": "Login",
  "Main": "Main",
  "My App": "My App",
  "Not Found": "Not Found",
  "Open": "Open",
  "Page Main": "Page Main",
  "Page about": "Page about",
  "Page profile": "Page profile",
  "Password": "Password",
  "Profile": "Profile",
  "Reload page": "Reload page",
  "Sign in": "Sign in",
  "Sign out": "Sign out",
  "Throw error": "Throw error",
  "Toggle sidebar": "Toggle sidebar",
  "Unexpected Error": "Unexpected Error",
  "Your firstname": "Your firstname",
  "Your lastname": "Your lastname",
  "_LanguageShort_": "_LanguageShort_",
  "_Language_": "_Language_"
}
